MANIFEST.in
setup.cfg
setup.py
versioneer.py
bin/fields2sispi
bin/plot_bands.py
bin/plot_bliss.py
bin/plot_bliss.py~
bin/plot_diagnostics.py
bin/plot_json
bin/plot_nightsum
bin/plot_progress
bin/schedule_chunk
bin/schedule_field
bin/schedule_night
bin/schedule_survey
bin/survey_prepare
bin/survey_scheduler
bin/survey_simulator
obztak/__init__.py
obztak/_version.py
obztak/bliss.py
obztak/ctio.py
obztak/factory.py
obztak/field.py
obztak/maglites.py
obztak/scheduler.py
obztak/survey.py
obztak/tactician.py
obztak.egg-info/PKG-INFO
obztak.egg-info/SOURCES.txt
obztak.egg-info/dependency_links.txt
obztak.egg-info/requires.txt
obztak.egg-info/top_level.txt
obztak/data/__init__.py
obztak/data/blanco_hour_angle_limits.dat
obztak/data/bliss-poly.txt
obztak/data/bliss-target-fields-p9v0-s45m30.csv
obztak/data/bliss-target-fields-p9v1-s45m30.csv
obztak/data/bliss-target-fields-p9v2-s45m30.csv
obztak/data/bliss-target-fields-p9v3-s45m30.csv
obztak/data/bliss-target-fields.csv
obztak/data/bliss-windows.csv
obztak/data/ccd_corners_xy_fill.dat
obztak/data/ctr-healpy-32-13131.txt
obztak/data/ctr-healpy-32-13131_v2.txt
obztak/data/maglites-poly.txt
obztak/data/maglites-target-fields.csv
obztak/data/maglites-windows.csv
obztak/data/round13-poly.txt
obztak/data/smash_fields_alltiles.txt
obztak/data/smash_fields_final.txt
obztak/scratch/__init__.py
obztak/scratch/coverage.py
obztak/scratch/dither.py
obztak/scratch/parse_standards.py
obztak/scratch/plot_characteristics.py
obztak/scratch/tiling.py
obztak/utils/__init__.py
obztak/utils/constants.py
obztak/utils/database.py
obztak/utils/date.py
obztak/utils/fileio.py
obztak/utils/movie.py
obztak/utils/ortho.py
obztak/utils/parser.py
obztak/utils/projector.py
obztak/utils/testing.py