Metadata-Version: 1.1
Name: obztak
Version: 3.0
Summary: Bizarro observation tactician for DECam
Home-page: https://github.com/obztak/obztak
Author: Alex Drlica-Wagner
Author-email: kadrlica@fnal.gov
License: UNKNOWN
Platform: any
Classifier: Development Status :: 2 - Pre-Alpha
Classifier: Intended Audience :: Science/Research
Classifier: Intended Audience :: Developers
Classifier: Programming Language :: Python
Classifier: Natural Language :: English
Classifier: Topic :: Scientific/Engineering
Classifier: Topic :: Scientific/Engineering :: Physics
Classifier: Topic :: Scientific/Engineering :: Astronomy
Classifier: Operating System :: MacOS
Classifier: Operating System :: POSIX
Classifier: License :: OSI Approved :: MIT License
